eyepop/__init__.py
eyepop/endpoint.py
eyepop/exceptions.py
eyepop/eyepopsdk.py
eyepop/jobs.py
eyepop/syncify.py
eyepop/visualize.py
eyepop_sdk_python-0.9.1.dist-info/LICENSE
eyepop_sdk_python-0.9.1.dist-info/METADATA
eyepop_sdk_python-0.9.1.dist-info/WHEEL
eyepop_sdk_python-0.9.1.dist-info/top_level.txt
eyepop_sdk_python-0.9.1.dist-info/RECORD
