Metadata-Version: 2.1
Name: eyepop-sdk-python
Version: 0.9.1
Summary: EyePop.ai Python SDK
Home-page: https://github.com/eyepop-ai/eyepop-sdk-python
Author: EyePop.ai
Author-email: info@eyepop.ai
License: MIT
Project-URL: Bug Tracker, https://github.com/eyepop-ai/eyepop-sdk-python/issues
Project-URL: Changes, https://github.com/eyepop-ai/eyepop-sdk-python/blob/master/CHANGELOG.md
Project-URL: Documentation, https://github.com/eyepop-ai/eyepop-sdk-python
Project-URL: Source Code, https://github.com/eyepop-ai/eyepop-sdk-python
Keywords: EyePop AI ML CV
Classifier: Development Status :: 5 - Production/Stable
Classifier: Intended Audience :: Developers
Classifier: License :: OSI Approved :: MIT License
Classifier: Operating System :: OS Independent
Classifier: Programming Language :: Python
Classifier: Programming Language :: Python :: 3
Classifier: Programming Language :: Python :: 3 :: Only
Classifier: Programming Language :: Python :: 3.8
Classifier: Programming Language :: Python :: 3.9
Classifier: Programming Language :: Python :: 3.10
Classifier: Programming Language :: Python :: 3.11
Classifier: Programming Language :: Python :: 3.12
Classifier: Topic :: Software Development :: Libraries :: Python Modules
Requires-Python: >=3.8
License-File: LICENSE
Requires-Dist: aiohttp >=3.9.1
Requires-Dist: matplotlib >=3.8.2
